{"is_source_file": true, "format": "TypeScript", "description": "This is the main entry point for an Angular application, responsible for bootstrapping the root component with the application configuration.", "external_files": ["@angular/platform-browser", "./app/app.config", "./app/app.component"], "external_methods": ["bootstrapApplication"], "published": [], "classes": [], "methods": [{"name": "bootstrapApplication", "description": "Initializes and bootstraps the Angular application with the specified root component and configuration."}], "calls": ["bootstrapApplication"], "search-terms": ["Angular", "main.ts", "bootstrapApplication", "AppComponent", "appConfig"], "state": 2, "file_id": 7, "knowledge_revision": 35, "git_revision": "f2f58bacb7af448d3b2cd230d9618f80fd3d6041", "ctags": [], "hash": "c986c915181c0d91d6ea1af9fc003131", "format-version": 4, "code-base-name": "notes_frontend", "filename": "notes_frontend/src/main.ts", "revision_history": [{"35": "f2f58bacb7af448d3b2cd230d9618f80fd3d6041"}]}